canvascli/__init__.py
canvascli/_version.py
canvascli/main.py
canvascli-0.7.0.dist-info/LICENSE
canvascli-0.7.0.dist-info/METADATA
canvascli-0.7.0.dist-info/WHEEL
canvascli-0.7.0.dist-info/entry_points.txt
canvascli-0.7.0.dist-info/top_level.txt
canvascli-0.7.0.dist-info/RECORD
