Metadata-Version: 2.1
Name: canvascli
Version: 0.7.0
Summary: A CLI to reformat and review Canvas grades
Home-page: https://github.com/joelostblom/canvascli
Author: Joel Ostblom
Author-email: joelostblom@protonmail.com
Requires-Python: >=3.8
License-File: LICENSE
Requires-Dist: altair >=5.0.0
Requires-Dist: canvasapi >=2.1.0
Requires-Dist: click >=8.0.0
Requires-Dist: pandas >=1.1.0
Requires-Dist: tabulate >=0.8.3
Requires-Dist: dataclassy >=0.10
Requires-Dist: luddite >=1.0
Requires-Dist: appdirs >=1.0
Requires-Dist: tqdm >=4.40
Requires-Dist: scipy >=1.4.0
